startracker/__init__.py
startracker/analysis/__init__.py
startracker/analysis/fitter.py
startracker/analysis/image.py
startracker/io/io.py
startracker/scripts/process_subrun.py
startracker/tools/image_producer.py
startracker/tools/star_fitter.py
startracker-0.1.0.dist-info/entry_points.txt
startracker-0.1.0.dist-info/LICENSE
startracker-0.1.0.dist-info/WHEEL
startracker-0.1.0.dist-info/METADATA
startracker-0.1.0.dist-info/RECORD
