Metadata-Version: 2.1
Name: startracker
Version: 0.1.0
Summary: Startracker
Author: Mykhailo Dalchenko
Author-email: mykhailo.dalchenko@unige.ch
Requires-Python: >=3.6
Classifier: License :: OSI Approved :: BSD License
Requires-Dist: lstchain~=0.7.3
Requires-Dist: ctapipe
Requires-Dist: simple_slurm
Requires-Dist: natsort
Requires-Dist: Deprecated
Requires-Dist: sphinx ; extra == "doc"
Requires-Dist: sphinx_rtd_theme ; extra == "doc"
Requires-Dist: recommonmark ; extra == "doc"
Requires-Dist: sphinx-argparse ; extra == "doc"
Requires-Dist: nbsphinx ; extra == "doc"
Provides-Extra: doc
